prophepy/__init__.py
prophepy/exceptions.py
prophepy-0.0.4.dist-info/LICENSE
prophepy-0.0.4.dist-info/WHEEL
prophepy-0.0.4.dist-info/METADATA
prophepy-0.0.4.dist-info/RECORD
